radhikalibrary/__init__.py
radhikalibrary/title.py
radhikalibrary-0.2.0.dist-info/METADATA
radhikalibrary-0.2.0.dist-info/WHEEL
radhikalibrary-0.2.0.dist-info/top_level.txt
radhikalibrary-0.2.0.dist-info/RECORD
