Metadata-Version: 2.1
Name: radhikalibrary
Version: 0.2.0
Summary: My for loop pattern Python library
Author: radhika
License: MIT
